qandle_ai/__init__.py
qandle_ai/qandle_client.py
qandle_ai-0.0.1.dist-info/licenses/LICENSE
qandle_ai-0.0.1.dist-info/METADATA
qandle_ai-0.0.1.dist-info/WHEEL
qandle_ai-0.0.1.dist-info/top_level.txt
qandle_ai-0.0.1.dist-info/RECORD
